Metadata-Version: 2.4
Name: greetings_helloworld2030_1
Version: 1.0.0
Summary: My package description
Author-email: Fabio Nelli <meccanismo.complesso@gmail.com>
Requires-Python: >=3.7
